{".class": "MypyFile", "_fullname": "controllers.weather", "is_partial_stub_package": false, "is_stub": false, "names": {".class": "SymbolTable", "SenseHat": {".class": "SymbolTableNode", "kind": "Gdef", "node": {".class": "Var", "flags": ["is_suppressed_import", "is_ready"], "fullname": "controllers.weather.SenseHat", "name": "SenseHat", "type": {".class": "AnyType", "missing_import_name": "controllers.weather.SenseHat", "source_any": null, "type_of_any": 3}}}, "__doc__": {".class": "SymbolTableNode", "kind": "Gdef", "node": {".class": "Var", "flags": ["is_ready"], "fullname": "controllers.weather.__doc__", "name": "__doc__", "type": "builtins.str"}}, "__file__": {".class": "SymbolTableNode", "kind": "Gdef", "node": {".class": "Var", "flags": ["is_ready"], "fullname": "controllers.weather.__file__", "name": "__file__", "type": "builtins.str"}}, "__name__": {".class": "SymbolTableNode", "kind": "Gdef", "node": {".class": "Var", "flags": ["is_ready"], "fullname": "controllers.weather.__name__", "name": "__name__", "type": "builtins.str"}}, "__package__": {".class": "SymbolTableNode", "kind": "Gdef", "node": {".class": "Var", "flags": ["is_ready"], "fullname": "controllers.weather.__package__", "name": "__package__", "type": "builtins.str"}}, "adjustTempForCpuTemp": {".class": "SymbolTableNode", "kind": "Gdef", "node": {".class": "FuncDef", "arg_kinds": [0], "arg_names": ["temp_c"], "flags": [], "fullname": "controllers.weather.adjustTempForCpuTemp", "name": "adjustTempForCpuTemp", "type": null}}, "asyncio": {".class": "SymbolTableNode", "cross_ref": "asyncio", "kind": "Gdef"}, "convertToF": {".class": "SymbolTableNode", "kind": "Gdef", "node": {".class": "FuncDef", "arg_kinds": [0], "arg_names": ["temp_c"], "flags": [], "fullname": "controllers.weather.convertToF", "name": "convertToF", "type": null}}, "datetime": {".class": "SymbolTableNode", "cross_ref": "datetime", "kind": "Gdef"}, "getAccelerometer": {".class": "SymbolTableNode", "kind": "Gdef", "node": {".class": "FuncDef", "arg_kinds": [], "arg_names": [], "flags": [], "fullname": "controllers.weather.getAccelerometer", "name": "getAccelerometer", "type": null}}, "getCPUTemp": {".class": "SymbolTableNode", "kind": "Gdef", "node": {".class": "FuncDef", "arg_kinds": [], "arg_names": [], "flags": [], "fullname": "controllers.weather.getCPUTemp", "name": "getCPUTemp", "type": null}}, "getCompass": {".class": "SymbolTableNode", "kind": "Gdef", "node": {".class": "FuncDef", "arg_kinds": [], "arg_names": [], "flags": [], "fullname": "controllers.weather.getCompass", "name": "getCompass", "type": null}}, "getGyroscope": {".class": "SymbolTableNode", "kind": "Gdef", "node": {".class": "FuncDef", "arg_kinds": [], "arg_names": [], "flags": [], "fullname": "controllers.weather.getGyroscope", "name": "getGyroscope", "type": null}}, "getHumidity": {".class": "SymbolTableNode", "kind": "Gdef", "node": {".class": "FuncDef", "arg_kinds": [], "arg_names": [], "flags": [], "fullname": "controllers.weather.getHumidity", "name": "getHumidity", "type": null}}, "getOrientation": {".class": "SymbolTableNode", "kind": "Gdef", "node": {".class": "FuncDef", "arg_kinds": [], "arg_names": [], "flags": [], "fullname": "controllers.weather.getOrientation", "name": "getOrientation", "type": null}}, "getOrientationDegrees": {".class": "SymbolTableNode", "kind": "Gdef", "node": {".class": "FuncDef", "arg_kinds": [], "arg_names": [], "flags": [], "fullname": "controllers.weather.getOrientationDegrees", "name": "getOrientationDegrees", "type": null}}, "getPressure": {".class": "SymbolTableNode", "kind": "Gdef", "node": {".class": "FuncDef", "arg_kinds": [], "arg_names": [], "flags": [], "fullname": "controllers.weather.getPressure", "name": "getPressure", "type": null}}, "getTemp": {".class": "SymbolTableNode", "kind": "Gdef", "node": {".class": "FuncDef", "arg_kinds": [], "arg_names": [], "flags": [], "fullname": "controllers.weather.getTemp", "name": "getTemp", "type": null}}, "load_dotenv": {".class": "SymbolTableNode", "cross_ref": "dotenv.main.load_dotenv", "kind": "Gdef"}, "os": {".class": "SymbolTableNode", "cross_ref": "os", "kind": "Gdef"}, "sense": {".class": "SymbolTableNode", "kind": "Gdef", "node": {".class": "Var", "flags": [], "fullname": "controllers.weather.sense", "name": "sense", "type": {".class": "AnyType", "missing_import_name": "controllers.weather.SenseHat", "source_any": {".class": "AnyType", "missing_import_name": "controllers.weather.SenseHat", "source_any": null, "type_of_any": 3}, "type_of_any": 7}}}, "setLowLight": {".class": "SymbolTableNode", "kind": "Gdef", "node": {".class": "FuncDef", "arg_kinds": [1], "arg_names": ["setting"], "flags": [], "fullname": "controllers.weather.setLowLight", "name": "setLowLight", "type": null}}, "showLetter": {".class": "SymbolTableNode", "kind": "Gdef", "node": {".class": "FuncDef", "arg_kinds": [0, 1, 1], "arg_names": ["letter", "text_colour", "back_colour"], "flags": [], "fullname": "controllers.weather.showLetter", "name": "showLetter", "type": null}}, "showMessage": {".class": "SymbolTableNode", "kind": "Gdef", "node": {".class": "FuncDef", "arg_kinds": [0, 1, 1, 1], "arg_names": ["message", "scroll_speed", "text_colour", "back_colour"], "flags": [], "fullname": "controllers.weather.showMessage", "name": "showMessage", "type": null}}, "sleep": {".class": "SymbolTableNode", "cross_ref": "time.sleep", "kind": "Gdef"}, "subprocess": {".class": "SymbolTableNode", "cross_ref": "subprocess", "kind": "Gdef"}, "tempSetBackground": {".class": "SymbolTableNode", "kind": "Gdef", "node": {".class": "FuncDef", "arg_kinds": [0], "arg_names": ["temp_c"], "flags": [], "fullname": "controllers.weather.tempSetBackground", "name": "tempSetBackground", "type": null}}, "time": {".class": "SymbolTableNode", "cross_ref": "time", "kind": "Gdef"}}, "path": "/home/joel/Documents/github/WeatherPi/weatherapp/src/controllers/weather.py"}